tentris/__init__.py
tentris/http_store.py
tentris/version.py
tentris-0.19.14b0.dist-info/licenses/LICENSE.md
tentris-0.19.14b0.dist-info/METADATA
tentris-0.19.14b0.dist-info/WHEEL
tentris-0.19.14b0.dist-info/top_level.txt
tentris-0.19.14b0.dist-info/RECORD
