Metadata-Version: 2.4
Name: tentris
Version: 0.19.14b0
Summary: Python bindings for using the RDF graph database Tentris RDF rdflib
Author-email: Tentris GmbH <info@tentris.io>
Maintainer-email: Tentris GmbH <info@tentris.io>
License-Expression: LicenseRef-Tentris-EULA-Beta
Project-URL: Homepage, https://tentris.io
Project-URL: Documentation, https://docs.tentris.io/running_with_python.html
Project-URL: Repository, https://github.com/tentris/tentris
Project-URL: Issues, https://github.com/tentris/tentris/issues
Project-URL: Changelog, https://github.com/tentris/tentris/releases
Project-URL: License, https://tentris.io/#eula
Keywords: tentris,knowledge graph,RDF,SPARQL,graph database,rdflib,semantic web
Classifier: Development Status :: 4 - Beta
Classifier: Intended Audience :: Developers
Classifier: Intended Audience :: System Administrators
Classifier: Topic :: Software Development
Classifier: Topic :: Database :: Database Engines/Servers
Classifier: Programming Language :: Python :: 3.12
Requires-Python: >=3.12
License-File: LICENSE.md
Requires-Dist: rdflib>=7.3
Dynamic: license-file
